suda.py
suda-0.2.2.dist-info/LICENSE
suda-0.2.2.dist-info/METADATA
suda-0.2.2.dist-info/WHEEL
suda-0.2.2.dist-info/entry_points.txt
suda-0.2.2.dist-info/top_level.txt
suda-0.2.2.dist-info/RECORD
