Metadata-Version: 2.1
Name: suda
Version: 0.2.2
Summary: Python library for implementing Special Uniques Detection Algorithm (SUDA) for measuring disclosure control risk in synthetic data
Home-page: https://github.com/scottbw/suda
Download-URL: https://github.com/scottbw/suda/tarball/0.2.2
Author: Scott Wilson
Author-email: scott.bradley.wilson@gmail.com
License: MIT
Classifier: Development Status :: 4 - Beta
Classifier: License :: OSI Approved :: MIT License
Classifier: Topic :: Scientific/Engineering :: Mathematics
Classifier: Topic :: Software Development :: Libraries :: Python Modules
Classifier: Programming Language :: Python :: 3.11
License-File: LICENSE
Requires-Dist: pandas
